README.rst
setup.cfg
setup.py
bin/subhd
subhd/__init__.py
subhd/archive_handlers.py
subhd/exceptions.py
subhd/interfaces.py
subhd/main.py
subhd/search.py
subhd/subtitle.py
subhd/utils.py
subhd.egg-info/PKG-INFO
subhd.egg-info/SOURCES.txt
subhd.egg-info/dependency_links.txt
subhd.egg-info/requires.txt
subhd.egg-info/top_level.txt