Metadata-Version: 1.0
Name: subhd
Version: 1.0.6
Summary: Yet another SubHD.com download client
Home-page: https://github.com/henry40408/subhd
Author: Heng-Yi Wu
Author-email: henry40408@gmail.com
License: UNKNOWN
Platform: UNKNOWN
